{"version": 0.6, "generator": "Overpass API 0.7.62.1 084b4234", "osm3s": {"timestamp_osm_base": "2024-10-05T10:48:45Z", "copyright": "The data included in this document is from www.openstreetmap.org. The data is made available under ODbL."}, "elements": [{"type": "node", "id": 4554762995, "lat": -36.153184, "lon": 146.6098681}, {"type": "node", "id": 4554762996, "lat": -36.1531739, "lon": 146.6099739}, {"type": "node", "id": 4554762997, "lat": -36.1532443, "lon": 146.6099615}, {"type": "node", "id": 4554762998, "lat": -36.1532477, "lon": 146.6099054}, {"type": "way", "id": 459684413, "nodes": [4554762995, 4554762996, 4554762997, 4554762998, 4554762995], "tags": {"amenity": "theatre", "building": "yes", "name": "Sound Shell"}}]}