{"version": 0.6, "generator": "Overpass API 0.7.62.1 084b4234", "osm3s": {"timestamp_osm_base": "2024-10-05T09:50:45Z", "copyright": "The data included in this document is from www.openstreetmap.org. The data is made available under ODbL."}, "elements": [{"type": "node", "id": 2693747056, "lat": -37.3710989, "lon": 141.2149912}, {"type": "node", "id": 2693747057, "lat": -37.3714575, "lon": 141.2174851}, {"type": "node", "id": 2693747058, "lat": -37.3738235, "lon": 141.2170817}, {"type": "node", "id": 2693747059, "lat": -37.373508, "lon": 141.2144207}, {"type": "node", "id": 5394283688, "lat": -37.7280937, "lon": 141.1370333}, {"type": "node", "id": 5394283689, "lat": -37.7281455, "lon": 141.1374969}, {"type": "node", "id": 5394283690, "lat": -37.7270574, "lon": 141.1376732}, {"type": "node", "id": 5394283691, "lat": -37.7268155, "lon": 141.1357095}, {"type": "node", "id": 5394283692, "lat": -37.7283391, "lon": 141.1354596}, {"type": "node", "id": 5394283693, "lat": -37.7285072, "lon": 141.1369517}, {"type": "way", "id": 263731959, "nodes": [2693747057, 2693747056, 2693747059, 2693747058, 2693747057], "tags": {"leisure": "park", "name": "Dergholm Recreation Reserve"}}, {"type": "way", "id": 559241620, "nodes": [5394283688, 5394283689, 5394283690, 5394283691, 5394283692, 5394283693, 5394283688], "tags": {"leisure": "park", "name": "Strathdownie Recreation Reserve"}}]}